wedata/__init__.py
wedata/feature_store/__init__.py
wedata/feature_store/client.py
wedata/feature_store/constants/__init__.py
wedata/feature_store/constants/constants.py
wedata/feature_store/entities/__init__.py
wedata/feature_store/entities/column_info.py
wedata/feature_store/entities/data_type.py
wedata/feature_store/entities/environment_variables.py
wedata/feature_store/entities/feature.py
wedata/feature_store/entities/feature_column_info.py
wedata/feature_store/entities/feature_function.py
wedata/feature_store/entities/feature_lookup.py
wedata/feature_store/entities/feature_spec.py
wedata/feature_store/entities/feature_spec_constants.py
wedata/feature_store/entities/feature_table.py
wedata/feature_store/entities/feature_table_info.py
wedata/feature_store/entities/function_info.py
wedata/feature_store/entities/on_demand_column_info.py
wedata/feature_store/entities/source_data_column_info.py
wedata/feature_store/entities/training_set.py
wedata/feature_store/feature_table_client/__init__.py
wedata/feature_store/feature_table_client/feature_table_client.py
wedata/feature_store/spark_client/__init__.py
wedata/feature_store/spark_client/spark_client.py
wedata/feature_store/training_set_client/__init__.py
wedata/feature_store/training_set_client/training_set_client.py
wedata/feature_store/utils/__init__.py
wedata/feature_store/utils/common_utils.py
wedata/feature_store/utils/feature_lookup_utils.py
wedata/feature_store/utils/feature_spec_utils.py
wedata/feature_store/utils/feature_utils.py
wedata/feature_store/utils/on_demand_utils.py
wedata/feature_store/utils/schema_utils.py
wedata/feature_store/utils/signature_utils.py
wedata/feature_store/utils/topological_sort.py
wedata/feature_store/utils/training_set_utils.py
wedata/feature_store/utils/uc_utils.py
wedata/feature_store/utils/validation_utils.py
wedata_feature_engineering-0.1.13.dist-info/METADATA
wedata_feature_engineering-0.1.13.dist-info/WHEEL
wedata_feature_engineering-0.1.13.dist-info/top_level.txt
wedata_feature_engineering-0.1.13.dist-info/RECORD
