Metadata-Version: 2.1
Name: wedata-feature-engineering
Version: 0.1.13
Summary: Wedata Feature Engineering Library
Home-page: 
Author: meahqian
Author-email: 
License: Apache 2.0
Classifier: Programming Language :: Python :: 3
Classifier: License :: OSI Approved :: Apache Software License
Classifier: Operating System :: OS Independent
Requires-Python: >=3.7
Requires-Dist: pyspark>=3.0.0
Requires-Dist: delta-spark>=1.0.0
Requires-Dist: pandas>=1.0.0
